mkvenv/__init__.py
mkvenv/mkvenv.py
mkvenv/data/__init__.py
mkvenv/data/ver
mkvenv-0.2.3.dist-info/DESCRIPTION.rst
mkvenv-0.2.3.dist-info/METADATA
mkvenv-0.2.3.dist-info/RECORD
mkvenv-0.2.3.dist-info/WHEEL
mkvenv-0.2.3.dist-info/entry_points.txt
mkvenv-0.2.3.dist-info/metadata.json
mkvenv-0.2.3.dist-info/top_level.txt
