Metadata-Version: 2.0
Name: mkvenv
Version: 0.2.3
Summary: Wrapper for virtualenv, pip, and wheel
Home-page: https://github.com/nhoffman/mkvenv
Author: Noah Hoffman
Author-email: noah.hoffman@gmail.com
License: UNKNOWN
Platform: UNKNOWN
Classifier: Development Status :: 3 - Alpha
Classifier: Environment :: Console
Classifier: Intended Audience :: Developers
Classifier: Intended Audience :: System Administrators
Classifier: Operating System :: POSIX
Classifier: Programming Language :: Python :: 2.7
